nyan_pytest/__init__.py
nyan_pytest/frames.py
nyan_pytest/plugin.py
nyan_pytest-0.1.5.dist-info/METADATA
nyan_pytest-0.1.5.dist-info/WHEEL
nyan_pytest-0.1.5.dist-info/entry_points.txt
nyan_pytest-0.1.5.dist-info/top_level.txt
nyan_pytest-0.1.5.dist-info/RECORD
