Metadata-Version: 2.4
Name: nyan_pytest
Version: 0.1.5
Summary: A nyan-cat inspired test reporter for pytest
Author: mrilikecoding
License: MIT
Classifier: Development Status :: 3 - Alpha
Classifier: Framework :: Pytest
Classifier: Programming Language :: Python :: 3
Classifier: Programming Language :: Python :: 3.8
Classifier: Programming Language :: Python :: 3.9
Classifier: Programming Language :: Python :: 3.10
Classifier: Programming Language :: Python :: 3.11
Classifier: Programming Language :: Python :: 3.12
Classifier: Programming Language :: Python :: 3.13
Classifier: Topic :: Software Development :: Testing
Requires-Python: >=3.8
Requires-Dist: pytest>=6.0.0
